README.md
setup.cfg
setup.py
dc_json/__init__.py
dc_json/api.py
dc_json/core.py
dc_json/mm.py
dc_json/utils.py
dc_json.egg-info/PKG-INFO
dc_json.egg-info/SOURCES.txt
dc_json.egg-info/dependency_links.txt
dc_json.egg-info/requires.txt
dc_json.egg-info/top_level.txt