Metadata-Version: 2.1
Name: dc-json
Version: 0.2.3
Summary: Easily serialize dataclasses to and from JSON
Home-page: https://github.com/Gulats/dc-json
Author: gulats
Author-email: bharat.gulati.certi@gmail.com
License: Unlicense
Keywords: dataclasses json
Platform: UNKNOWN
Requires-Python: >=3.6
Provides-Extra: dev
